pysochrone-0.1.1.dist-info/METADATA
pysochrone-0.1.1.dist-info/WHEEL
pysochrone/__init__.py
pysochrone/pysochrone.cp39-win_amd64.pyd
pysochrone-0.1.1.dist-info/RECORD
