Metadata-Version: 2.1
Name: pysochrone
Version: 0.1.1
Classifier: Programming Language :: Rust
Classifier: Programming Language :: Python :: Implementation :: CPython
Classifier: Programming Language :: Python :: Implementation :: PyPy
Summary: This library provides a set of tools for generating isochrones from geographic coordinates. It leverages OpenStreetMap data to construct road networks and calculate areas accessible within specified time limits. The library is designed for both Rust and Python, offering high performance and easy integration into data science workflows.
Keywords: OpenStreetMaps,Isochrone,Mobility,Geo,Petgraph
License: MIT
Requires-Python: >=3.8
Project-URL: Source Code, https://github.com/kyleloving/osm_graph/tree/main
